{
  "date": "2026-07-02",
  "updated_at": "2026-07-02T11:17:29.227Z",
  "points": [
    {
      "ms": 1782964888904,
      "time": "0000",
      "fetched_at": "2026-07-02T04:01:28.904Z",
      "source": "queue-times",
      "summary": {
        "count": 20,
        "open_count": 8,
        "average_wait": 0,
        "max_wait": 0
      }
    },
    {
      "ms": 1782965786939,
      "time": "0010",
      "fetched_at": "2026-07-02T04:16:26.939Z",
      "source": "queue-times",
      "summary": {
        "count": 20,
        "open_count": 10,
        "average_wait": 10,
        "max_wait": 10
      }
    },
    {
      "ms": 1782966682089,
      "time": "0030",
      "fetched_at": "2026-07-02T04:31:22.089Z",
      "source": "queue-times",
      "summary": {
        "count": 20,
        "open_count": 10,
        "average_wait": 10,
        "max_wait": 10
      }
    },
    {
      "ms": 1782967588357,
      "time": "0040",
      "fetched_at": "2026-07-02T04:46:28.357Z",
      "source": "queue-times",
      "summary": {
        "count": 20,
        "open_count": 10,
        "average_wait": 10,
        "max_wait": 10
      }
    },
    {
      "ms": 1782968485696,
      "time": "0100",
      "fetched_at": "2026-07-02T05:01:25.696Z",
      "source": "queue-times",
      "summary": {
        "count": 20,
        "open_count": 10,
        "average_wait": 10,
        "max_wait": 10
      }
    },
    {
      "ms": 1782969386341,
      "time": "0110",
      "fetched_at": "2026-07-02T05:16:26.341Z",
      "source": "queue-times",
      "summary": {
        "count": 20,
        "open_count": 10,
        "average_wait": 10,
        "max_wait": 10
      }
    },
    {
      "ms": 1782970701996,
      "time": "0130",
      "fetched_at": "2026-07-02T05:38:21.996Z",
      "source": "queue-times",
      "summary": {
        "count": 20,
        "open_count": 10,
        "average_wait": 10,
        "max_wait": 10
      }
    },
    {
      "ms": 1782971186649,
      "time": "0140",
      "fetched_at": "2026-07-02T05:46:26.649Z",
      "source": "queue-times",
      "summary": {
        "count": 20,
        "open_count": 10,
        "average_wait": 10,
        "max_wait": 10
      }
    },
    {
      "ms": 1782972074597,
      "time": "0200",
      "fetched_at": "2026-07-02T06:01:14.597Z",
      "source": "queue-times",
      "summary": {
        "count": 20,
        "open_count": 10,
        "average_wait": 10,
        "max_wait": 10
      }
    },
    {
      "ms": 1782972979895,
      "time": "0210",
      "fetched_at": "2026-07-02T06:16:19.895Z",
      "source": "queue-times",
      "summary": {
        "count": 20,
        "open_count": 10,
        "average_wait": 10,
        "max_wait": 10
      }
    },
    {
      "ms": 1782973881610,
      "time": "0230",
      "fetched_at": "2026-07-02T06:31:21.610Z",
      "source": "queue-times",
      "summary": {
        "count": 20,
        "open_count": 10,
        "average_wait": 10,
        "max_wait": 10
      }
    },
    {
      "ms": 1782974800446,
      "time": "0240",
      "fetched_at": "2026-07-02T06:46:40.446Z",
      "source": "queue-times",
      "summary": {
        "count": 20,
        "open_count": 10,
        "average_wait": 10,
        "max_wait": 10
      }
    },
    {
      "ms": 1782975679402,
      "time": "0300",
      "fetched_at": "2026-07-02T07:01:19.402Z",
      "source": "queue-times",
      "summary": {
        "count": 20,
        "open_count": 10,
        "average_wait": 10,
        "max_wait": 10
      }
    },
    {
      "ms": 1782976585226,
      "time": "0310",
      "fetched_at": "2026-07-02T07:16:25.226Z",
      "source": "queue-times",
      "summary": {
        "count": 20,
        "open_count": 10,
        "average_wait": 10,
        "max_wait": 10
      }
    },
    {
      "ms": 1782977482864,
      "time": "0330",
      "fetched_at": "2026-07-02T07:31:22.864Z",
      "source": "queue-times",
      "summary": {
        "count": 20,
        "open_count": 10,
        "average_wait": 10,
        "max_wait": 10
      }
    },
    {
      "ms": 1782978384835,
      "time": "0340",
      "fetched_at": "2026-07-02T07:46:24.835Z",
      "source": "queue-times",
      "summary": {
        "count": 20,
        "open_count": 10,
        "average_wait": 10,
        "max_wait": 10
      }
    },
    {
      "ms": 1782979285091,
      "time": "0400",
      "fetched_at": "2026-07-02T08:01:25.091Z",
      "source": "queue-times",
      "summary": {
        "count": 20,
        "open_count": 10,
        "average_wait": 10,
        "max_wait": 10
      }
    },
    {
      "ms": 1782980189679,
      "time": "0410",
      "fetched_at": "2026-07-02T08:16:29.679Z",
      "source": "queue-times",
      "summary": {
        "count": 20,
        "open_count": 4,
        "average_wait": 0,
        "max_wait": 0
      }
    },
    {
      "ms": 1782981217958,
      "time": "0430",
      "fetched_at": "2026-07-02T08:33:37.958Z",
      "source": "queue-times",
      "summary": {
        "count": 20,
        "open_count": 4,
        "average_wait": 0,
        "max_wait": 0
      }
    },
    {
      "ms": 1782981975215,
      "time": "0440",
      "fetched_at": "2026-07-02T08:46:15.215Z",
      "source": "queue-times",
      "summary": {
        "count": 20,
        "open_count": 4,
        "average_wait": 0,
        "max_wait": 0
      }
    },
    {
      "ms": 1782982887593,
      "time": "0500",
      "fetched_at": "2026-07-02T09:01:27.593Z",
      "source": "queue-times",
      "summary": {
        "count": 20,
        "open_count": 4,
        "average_wait": 0,
        "max_wait": 0
      }
    },
    {
      "ms": 1782983789743,
      "time": "0510",
      "fetched_at": "2026-07-02T09:16:29.743Z",
      "source": "queue-times",
      "summary": {
        "count": 20,
        "open_count": 4,
        "average_wait": 0,
        "max_wait": 0
      }
    },
    {
      "ms": 1782984684485,
      "time": "0530",
      "fetched_at": "2026-07-02T09:31:24.485Z",
      "source": "queue-times",
      "summary": {
        "count": 20,
        "open_count": 4,
        "average_wait": 0,
        "max_wait": 0
      }
    },
    {
      "ms": 1782985575697,
      "time": "0540",
      "fetched_at": "2026-07-02T09:46:15.697Z",
      "source": "queue-times",
      "summary": {
        "count": 20,
        "open_count": 4,
        "average_wait": 0,
        "max_wait": 0
      }
    },
    {
      "ms": 1782986500497,
      "time": "0600",
      "fetched_at": "2026-07-02T10:01:40.497Z",
      "source": "queue-times",
      "summary": {
        "count": 20,
        "open_count": 4,
        "average_wait": 0,
        "max_wait": 0
      }
    },
    {
      "ms": 1782987407613,
      "time": "0610",
      "fetched_at": "2026-07-02T10:16:47.613Z",
      "source": "queue-times",
      "summary": {
        "count": 20,
        "open_count": 4,
        "average_wait": 0,
        "max_wait": 0
      }
    },
    {
      "ms": 1782988296014,
      "time": "0630",
      "fetched_at": "2026-07-02T10:31:36.014Z",
      "source": "queue-times",
      "summary": {
        "count": 20,
        "open_count": 4,
        "average_wait": 0,
        "max_wait": 0
      }
    },
    {
      "ms": 1782989185878,
      "time": "0640",
      "fetched_at": "2026-07-02T10:46:25.878Z",
      "source": "queue-times",
      "summary": {
        "count": 20,
        "open_count": 4,
        "average_wait": 0,
        "max_wait": 0
      }
    },
    {
      "ms": 1782990090232,
      "time": "0700",
      "fetched_at": "2026-07-02T11:01:30.232Z",
      "source": "queue-times",
      "summary": {
        "count": 20,
        "open_count": 4,
        "average_wait": 0,
        "max_wait": 0
      }
    },
    {
      "ms": 1782991049112,
      "time": "0710",
      "fetched_at": "2026-07-02T11:17:29.112Z",
      "source": "queue-times",
      "summary": {
        "count": 20,
        "open_count": 4,
        "average_wait": 0,
        "max_wait": 0
      }
    }
  ],
  "attractions": {
    "a-ak-657": {
      "name_en": "Festival of the Lion King",
      "name_ja": "Festival of the Lion King",
      "waits": [
        null,
        null,
        null,
        null,
        null,
        null,
        null,
        null,
        null,
        null,
        null,
        null,
        null,
        null,
        null,
        null,
        null,
        null,
        null,
        null,
        null,
        null,
        null,
        null,
        null,
        null,
        null,
        null,
        null,
        null
      ],
      "opens": [
        true,
        true,
        true,
        true,
        true,
        true,
        true,
        true,
        true,
        true,
        true,
        true,
        true,
        true,
        true,
        true,
        true,
        true,
        true,
        true,
        true,
        true,
        true,
        true,
        true,
        true,
        true,
        true,
        true,
        true
      ],
      "statuses": [
        "OPERATING",
        "OPERATING",
        "OPERATING",
        "OPERATING",
        "OPERATING",
        "OPERATING",
        "OPERATING",
        "OPERATING",
        "OPERATING",
        "OPERATING",
        "OPERATING",
        "OPERATING",
        "OPERATING",
        "OPERATING",
        "OPERATING",
        "OPERATING",
        "OPERATING",
        "OPERATING",
        "OPERATING",
        "OPERATING",
        "OPERATING",
        "OPERATING",
        "OPERATING",
        "OPERATING",
        "OPERATING",
        "OPERATING",
        "OPERATING",
        "OPERATING",
        "OPERATING",
        "OPERATING"
      ],
      "access_modes": [
        "STANDBY",
        "STANDBY",
        "STANDBY",
        "STANDBY",
        "STANDBY",
        "STANDBY",
        "STANDBY",
        "STANDBY",
        "STANDBY",
        "STANDBY",
        "STANDBY",
        "STANDBY",
        "STANDBY",
        "STANDBY",
        "STANDBY",
        "STANDBY",
        "STANDBY",
        "STANDBY",
        "STANDBY",
        "STANDBY",
        "STANDBY",
        "STANDBY",
        "STANDBY",
        "STANDBY",
        "STANDBY",
        "STANDBY",
        "STANDBY",
        "STANDBY",
        "STANDBY",
        "STANDBY"
      ]
    },
    "a-ak-651": {
      "name_en": "Gorilla Falls Exploration Trail",
      "name_ja": "Gorilla Falls Exploration Trail",
      "waits": [
        null,
        null,
        null,
        null,
        null,
        null,
        null,
        null,
        null,
        null,
        null,
        null,
        null,
        null,
        null,
        null,
        null,
        null,
        null,
        null,
        null,
        null,
        null,
        null,
        null,
        null,
        null,
        null,
        null,
        null
      ],
      "opens": [
        false,
        false,
        false,
        false,
        false,
        false,
        false,
        false,
        false,
        false,
        false,
        false,
        false,
        false,
        false,
        false,
        false,
        false,
        false,
        false,
        false,
        false,
        false,
        false,
        false,
        false,
        false,
        false,
        false,
        false
      ],
      "statuses": [
        "NO_INFO",
        "NO_INFO",
        "NO_INFO",
        "NO_INFO",
        "NO_INFO",
        "NO_INFO",
        "NO_INFO",
        "NO_INFO",
        "NO_INFO",
        "NO_INFO",
        "NO_INFO",
        "NO_INFO",
        "NO_INFO",
        "NO_INFO",
        "NO_INFO",
        "NO_INFO",
        "NO_INFO",
        "NO_INFO",
        "NO_INFO",
        "NO_INFO",
        "NO_INFO",
        "NO_INFO",
        "NO_INFO",
        "NO_INFO",
        "NO_INFO",
        "NO_INFO",
        "NO_INFO",
        "NO_INFO",
        "NO_INFO",
        "NO_INFO"
      ],
      "access_modes": [
        "STANDBY",
        "STANDBY",
        "STANDBY",
        "STANDBY",
        "STANDBY",
        "STANDBY",
        "STANDBY",
        "STANDBY",
        "STANDBY",
        "STANDBY",
        "STANDBY",
        "STANDBY",
        "STANDBY",
        "STANDBY",
        "STANDBY",
        "STANDBY",
        "STANDBY",
        "STANDBY",
        "STANDBY",
        "STANDBY",
        "STANDBY",
        "STANDBY",
        "STANDBY",
        "STANDBY",
        "STANDBY",
        "STANDBY",
        "STANDBY",
        "STANDBY",
        "STANDBY",
        "STANDBY"
      ]
    },
    "a-ak-113": {
      "name_en": "Kilimanjaro Safaris",
      "name_ja": "キリマンジャロ・サファリ",
      "waits": [
        null,
        null,
        null,
        null,
        null,
        null,
        null,
        null,
        null,
        null,
        null,
        null,
        null,
        null,
        null,
        null,
        null,
        null,
        null,
        null,
        null,
        null,
        null,
        null,
        null,
        null,
        null,
        null,
        null,
        null
      ],
      "opens": [
        false,
        false,
        false,
        false,
        false,
        false,
        false,
        false,
        false,
        false,
        false,
        false,
        false,
        false,
        false,
        false,
        false,
        false,
        false,
        false,
        false,
        false,
        false,
        false,
        false,
        false,
        false,
        false,
        false,
        false
      ],
      "statuses": [
        "NO_INFO",
        "NO_INFO",
        "NO_INFO",
        "NO_INFO",
        "NO_INFO",
        "NO_INFO",
        "NO_INFO",
        "NO_INFO",
        "NO_INFO",
        "NO_INFO",
        "NO_INFO",
        "NO_INFO",
        "NO_INFO",
        "NO_INFO",
        "NO_INFO",
        "NO_INFO",
        "NO_INFO",
        "NO_INFO",
        "NO_INFO",
        "NO_INFO",
        "NO_INFO",
        "NO_INFO",
        "NO_INFO",
        "NO_INFO",
        "NO_INFO",
        "NO_INFO",
        "NO_INFO",
        "NO_INFO",
        "NO_INFO",
        "NO_INFO"
      ],
      "access_modes": [
        "STANDBY",
        "STANDBY",
        "STANDBY",
        "STANDBY",
        "STANDBY",
        "STANDBY",
        "STANDBY",
        "STANDBY",
        "STANDBY",
        "STANDBY",
        "STANDBY",
        "STANDBY",
        "STANDBY",
        "STANDBY",
        "STANDBY",
        "STANDBY",
        "STANDBY",
        "STANDBY",
        "STANDBY",
        "STANDBY",
        "STANDBY",
        "STANDBY",
        "STANDBY",
        "STANDBY",
        "STANDBY",
        "STANDBY",
        "STANDBY",
        "STANDBY",
        "STANDBY",
        "STANDBY"
      ]
    },
    "a-ak-655": {
      "name_en": "Wildlife Express Train",
      "name_ja": "Wildlife Express Train",
      "waits": [
        null,
        null,
        null,
        null,
        null,
        null,
        null,
        null,
        null,
        null,
        null,
        null,
        null,
        null,
        null,
        null,
        null,
        null,
        null,
        null,
        null,
        null,
        null,
        null,
        null,
        null,
        null,
        null,
        null,
        null
      ],
      "opens": [
        false,
        false,
        false,
        false,
        false,
        false,
        false,
        false,
        false,
        false,
        false,
        false,
        false,
        false,
        false,
        false,
        false,
        false,
        false,
        false,
        false,
        false,
        false,
        false,
        false,
        false,
        false,
        false,
        false,
        false
      ],
      "statuses": [
        "NO_INFO",
        "NO_INFO",
        "NO_INFO",
        "NO_INFO",
        "NO_INFO",
        "NO_INFO",
        "NO_INFO",
        "NO_INFO",
        "NO_INFO",
        "NO_INFO",
        "NO_INFO",
        "NO_INFO",
        "NO_INFO",
        "NO_INFO",
        "NO_INFO",
        "NO_INFO",
        "NO_INFO",
        "NO_INFO",
        "NO_INFO",
        "NO_INFO",
        "NO_INFO",
        "NO_INFO",
        "NO_INFO",
        "NO_INFO",
        "NO_INFO",
        "NO_INFO",
        "NO_INFO",
        "NO_INFO",
        "NO_INFO",
        "NO_INFO"
      ],
      "access_modes": [
        "STANDBY",
        "STANDBY",
        "STANDBY",
        "STANDBY",
        "STANDBY",
        "STANDBY",
        "STANDBY",
        "STANDBY",
        "STANDBY",
        "STANDBY",
        "STANDBY",
        "STANDBY",
        "STANDBY",
        "STANDBY",
        "STANDBY",
        "STANDBY",
        "STANDBY",
        "STANDBY",
        "STANDBY",
        "STANDBY",
        "STANDBY",
        "STANDBY",
        "STANDBY",
        "STANDBY",
        "STANDBY",
        "STANDBY",
        "STANDBY",
        "STANDBY",
        "STANDBY",
        "STANDBY"
      ]
    },
    "a-ak-110": {
      "name_en": "Expedition Everest - Legend of the Forbidden Mountain",
      "name_ja": "エクスペディション・エベレスト",
      "waits": [
        null,
        null,
        null,
        null,
        null,
        null,
        null,
        null,
        null,
        null,
        null,
        null,
        null,
        null,
        null,
        null,
        null,
        null,
        null,
        null,
        null,
        null,
        null,
        null,
        null,
        null,
        null,
        null,
        null,
        null
      ],
      "opens": [
        false,
        false,
        false,
        false,
        false,
        false,
        false,
        false,
        false,
        false,
        false,
        false,
        false,
        false,
        false,
        false,
        false,
        false,
        false,
        false,
        false,
        false,
        false,
        false,
        false,
        false,
        false,
        false,
        false,
        false
      ],
      "statuses": [
        "NO_INFO",
        "NO_INFO",
        "NO_INFO",
        "NO_INFO",
        "NO_INFO",
        "NO_INFO",
        "NO_INFO",
        "NO_INFO",
        "NO_INFO",
        "NO_INFO",
        "NO_INFO",
        "NO_INFO",
        "NO_INFO",
        "NO_INFO",
        "NO_INFO",
        "NO_INFO",
        "NO_INFO",
        "NO_INFO",
        "NO_INFO",
        "NO_INFO",
        "NO_INFO",
        "NO_INFO",
        "NO_INFO",
        "NO_INFO",
        "NO_INFO",
        "NO_INFO",
        "NO_INFO",
        "NO_INFO",
        "NO_INFO",
        "NO_INFO"
      ],
      "access_modes": [
        "STANDBY",
        "STANDBY",
        "STANDBY",
        "STANDBY",
        "STANDBY",
        "STANDBY",
        "STANDBY",
        "STANDBY",
        "STANDBY",
        "STANDBY",
        "STANDBY",
        "STANDBY",
        "STANDBY",
        "STANDBY",
        "STANDBY",
        "STANDBY",
        "STANDBY",
        "STANDBY",
        "STANDBY",
        "STANDBY",
        "STANDBY",
        "STANDBY",
        "STANDBY",
        "STANDBY",
        "STANDBY",
        "STANDBY",
        "STANDBY",
        "STANDBY",
        "STANDBY",
        "STANDBY"
      ]
    },
    "a-ak-14533": {
      "name_en": "Expedition Everest - Legend of the Forbidden Mountain Single Rider",
      "name_ja": "エクスペディション・エベレスト",
      "waits": [
        null,
        null,
        null,
        null,
        null,
        null,
        null,
        null,
        null,
        null,
        null,
        null,
        null,
        null,
        null,
        null,
        null,
        null,
        null,
        null,
        null,
        null,
        null,
        null,
        null,
        null,
        null,
        null,
        null,
        null
      ],
      "opens": [
        false,
        false,
        false,
        false,
        false,
        false,
        false,
        false,
        false,
        false,
        false,
        false,
        false,
        false,
        false,
        false,
        false,
        false,
        false,
        false,
        false,
        false,
        false,
        false,
        false,
        false,
        false,
        false,
        false,
        false
      ],
      "statuses": [
        "NO_INFO",
        "NO_INFO",
        "NO_INFO",
        "NO_INFO",
        "NO_INFO",
        "NO_INFO",
        "NO_INFO",
        "NO_INFO",
        "NO_INFO",
        "NO_INFO",
        "NO_INFO",
        "NO_INFO",
        "NO_INFO",
        "NO_INFO",
        "NO_INFO",
        "NO_INFO",
        "NO_INFO",
        "NO_INFO",
        "NO_INFO",
        "NO_INFO",
        "NO_INFO",
        "NO_INFO",
        "NO_INFO",
        "NO_INFO",
        "NO_INFO",
        "NO_INFO",
        "NO_INFO",
        "NO_INFO",
        "NO_INFO",
        "NO_INFO"
      ],
      "access_modes": [
        "STANDBY",
        "STANDBY",
        "STANDBY",
        "STANDBY",
        "STANDBY",
        "STANDBY",
        "STANDBY",
        "STANDBY",
        "STANDBY",
        "STANDBY",
        "STANDBY",
        "STANDBY",
        "STANDBY",
        "STANDBY",
        "STANDBY",
        "STANDBY",
        "STANDBY",
        "STANDBY",
        "STANDBY",
        "STANDBY",
        "STANDBY",
        "STANDBY",
        "STANDBY",
        "STANDBY",
        "STANDBY",
        "STANDBY",
        "STANDBY",
        "STANDBY",
        "STANDBY",
        "STANDBY"
      ]
    },
    "a-ak-10921": {
      "name_en": "Feathered Friends in Flight!",
      "name_ja": "Feathered Friends in Flight!",
      "waits": [
        null,
        null,
        null,
        null,
        null,
        null,
        null,
        null,
        null,
        null,
        null,
        null,
        null,
        null,
        null,
        null,
        null,
        null,
        null,
        null,
        null,
        null,
        null,
        null,
        null,
        null,
        null,
        null,
        null,
        null
      ],
      "opens": [
        true,
        true,
        true,
        true,
        true,
        true,
        true,
        true,
        true,
        true,
        true,
        true,
        true,
        true,
        true,
        true,
        true,
        true,
        true,
        true,
        true,
        true,
        true,
        true,
        true,
        true,
        true,
        true,
        true,
        true
      ],
      "statuses": [
        "OPERATING",
        "OPERATING",
        "OPERATING",
        "OPERATING",
        "OPERATING",
        "OPERATING",
        "OPERATING",
        "OPERATING",
        "OPERATING",
        "OPERATING",
        "OPERATING",
        "OPERATING",
        "OPERATING",
        "OPERATING",
        "OPERATING",
        "OPERATING",
        "OPERATING",
        "OPERATING",
        "OPERATING",
        "OPERATING",
        "OPERATING",
        "OPERATING",
        "OPERATING",
        "OPERATING",
        "OPERATING",
        "OPERATING",
        "OPERATING",
        "OPERATING",
        "OPERATING",
        "OPERATING"
      ],
      "access_modes": [
        "STANDBY",
        "STANDBY",
        "STANDBY",
        "STANDBY",
        "STANDBY",
        "STANDBY",
        "STANDBY",
        "STANDBY",
        "STANDBY",
        "STANDBY",
        "STANDBY",
        "STANDBY",
        "STANDBY",
        "STANDBY",
        "STANDBY",
        "STANDBY",
        "STANDBY",
        "STANDBY",
        "STANDBY",
        "STANDBY",
        "STANDBY",
        "STANDBY",
        "STANDBY",
        "STANDBY",
        "STANDBY",
        "STANDBY",
        "STANDBY",
        "STANDBY",
        "STANDBY",
        "STANDBY"
      ]
    },
    "a-ak-112": {
      "name_en": "Kali River Rapids",
      "name_ja": "Kali River Rapids",
      "waits": [
        null,
        null,
        null,
        null,
        null,
        null,
        null,
        null,
        null,
        null,
        null,
        null,
        null,
        null,
        null,
        null,
        null,
        null,
        null,
        null,
        null,
        null,
        null,
        null,
        null,
        null,
        null,
        null,
        null,
        null
      ],
      "opens": [
        false,
        false,
        false,
        false,
        false,
        false,
        false,
        false,
        false,
        false,
        false,
        false,
        false,
        false,
        false,
        false,
        false,
        false,
        false,
        false,
        false,
        false,
        false,
        false,
        false,
        false,
        false,
        false,
        false,
        false
      ],
      "statuses": [
        "NO_INFO",
        "NO_INFO",
        "NO_INFO",
        "NO_INFO",
        "NO_INFO",
        "NO_INFO",
        "NO_INFO",
        "NO_INFO",
        "NO_INFO",
        "NO_INFO",
        "NO_INFO",
        "NO_INFO",
        "NO_INFO",
        "NO_INFO",
        "NO_INFO",
        "NO_INFO",
        "NO_INFO",
        "NO_INFO",
        "NO_INFO",
        "NO_INFO",
        "NO_INFO",
        "NO_INFO",
        "NO_INFO",
        "NO_INFO",
        "NO_INFO",
        "NO_INFO",
        "NO_INFO",
        "NO_INFO",
        "NO_INFO",
        "NO_INFO"
      ],
      "access_modes": [
        "STANDBY",
        "STANDBY",
        "STANDBY",
        "STANDBY",
        "STANDBY",
        "STANDBY",
        "STANDBY",
        "STANDBY",
        "STANDBY",
        "STANDBY",
        "STANDBY",
        "STANDBY",
        "STANDBY",
        "STANDBY",
        "STANDBY",
        "STANDBY",
        "STANDBY",
        "STANDBY",
        "STANDBY",
        "STANDBY",
        "STANDBY",
        "STANDBY",
        "STANDBY",
        "STANDBY",
        "STANDBY",
        "STANDBY",
        "STANDBY",
        "STANDBY",
        "STANDBY",
        "STANDBY"
      ]
    },
    "a-ak-13806": {
      "name_en": "Animal Care at Conservation Station",
      "name_ja": "Animal Care at Conservation Station",
      "waits": [
        null,
        null,
        null,
        null,
        null,
        null,
        null,
        null,
        null,
        null,
        null,
        null,
        null,
        null,
        null,
        null,
        null,
        null,
        null,
        null,
        null,
        null,
        null,
        null,
        null,
        null,
        null,
        null,
        null,
        null
      ],
      "opens": [
        true,
        true,
        true,
        true,
        true,
        true,
        true,
        true,
        true,
        true,
        true,
        true,
        true,
        true,
        true,
        true,
        true,
        false,
        false,
        false,
        false,
        false,
        false,
        false,
        false,
        false,
        false,
        false,
        false,
        false
      ],
      "statuses": [
        "OPERATING",
        "OPERATING",
        "OPERATING",
        "OPERATING",
        "OPERATING",
        "OPERATING",
        "OPERATING",
        "OPERATING",
        "OPERATING",
        "OPERATING",
        "OPERATING",
        "OPERATING",
        "OPERATING",
        "OPERATING",
        "OPERATING",
        "OPERATING",
        "OPERATING",
        "DOWN",
        "DOWN",
        "DOWN",
        "DOWN",
        "DOWN",
        "DOWN",
        "DOWN",
        "DOWN",
        "DOWN",
        "DOWN",
        "DOWN",
        "DOWN",
        "DOWN"
      ],
      "access_modes": [
        "STANDBY",
        "STANDBY",
        "STANDBY",
        "STANDBY",
        "STANDBY",
        "STANDBY",
        "STANDBY",
        "STANDBY",
        "STANDBY",
        "STANDBY",
        "STANDBY",
        "STANDBY",
        "STANDBY",
        "STANDBY",
        "STANDBY",
        "STANDBY",
        "STANDBY",
        "STANDBY",
        "STANDBY",
        "STANDBY",
        "STANDBY",
        "STANDBY",
        "STANDBY",
        "STANDBY",
        "STANDBY",
        "STANDBY",
        "STANDBY",
        "STANDBY",
        "STANDBY",
        "STANDBY"
      ]
    },
    "a-ak-16545": {
      "name_en": "Bluey's Wild World at Conservation Station",
      "name_ja": "Bluey's Wild World at Conservation Station",
      "waits": [
        null,
        10,
        10,
        10,
        10,
        10,
        10,
        10,
        10,
        10,
        10,
        10,
        10,
        10,
        10,
        10,
        10,
        null,
        null,
        null,
        null,
        null,
        null,
        null,
        null,
        null,
        null,
        null,
        null,
        null
      ],
      "opens": [
        false,
        true,
        true,
        true,
        true,
        true,
        true,
        true,
        true,
        true,
        true,
        true,
        true,
        true,
        true,
        true,
        true,
        false,
        false,
        false,
        false,
        false,
        false,
        false,
        false,
        false,
        false,
        false,
        false,
        false
      ],
      "statuses": [
        "NO_INFO",
        "OPERATING",
        "OPERATING",
        "OPERATING",
        "OPERATING",
        "OPERATING",
        "OPERATING",
        "OPERATING",
        "OPERATING",
        "OPERATING",
        "OPERATING",
        "OPERATING",
        "OPERATING",
        "OPERATING",
        "OPERATING",
        "OPERATING",
        "OPERATING",
        "DOWN",
        "DOWN",
        "DOWN",
        "DOWN",
        "DOWN",
        "DOWN",
        "DOWN",
        "DOWN",
        "DOWN",
        "DOWN",
        "DOWN",
        "DOWN",
        "DOWN"
      ],
      "access_modes": [
        "STANDBY",
        "STANDBY",
        "STANDBY",
        "STANDBY",
        "STANDBY",
        "STANDBY",
        "STANDBY",
        "STANDBY",
        "STANDBY",
        "STANDBY",
        "STANDBY",
        "STANDBY",
        "STANDBY",
        "STANDBY",
        "STANDBY",
        "STANDBY",
        "STANDBY",
        "STANDBY",
        "STANDBY",
        "STANDBY",
        "STANDBY",
        "STANDBY",
        "STANDBY",
        "STANDBY",
        "STANDBY",
        "STANDBY",
        "STANDBY",
        "STANDBY",
        "STANDBY",
        "STANDBY"
      ]
    },
    "a-ak-10920": {
      "name_en": "Finding Nemo: The Big Blue... and Beyond!",
      "name_ja": "Finding Nemo: The Big Blue... and Beyond!",
      "waits": [
        null,
        null,
        null,
        null,
        null,
        null,
        null,
        null,
        null,
        null,
        null,
        null,
        null,
        null,
        null,
        null,
        null,
        null,
        null,
        null,
        null,
        null,
        null,
        null,
        null,
        null,
        null,
        null,
        null,
        null
      ],
      "opens": [
        true,
        true,
        true,
        true,
        true,
        true,
        true,
        true,
        true,
        true,
        true,
        true,
        true,
        true,
        true,
        true,
        true,
        true,
        true,
        true,
        true,
        true,
        true,
        true,
        true,
        true,
        true,
        true,
        true,
        true
      ],
      "statuses": [
        "OPERATING",
        "OPERATING",
        "OPERATING",
        "OPERATING",
        "OPERATING",
        "OPERATING",
        "OPERATING",
        "OPERATING",
        "OPERATING",
        "OPERATING",
        "OPERATING",
        "OPERATING",
        "OPERATING",
        "OPERATING",
        "OPERATING",
        "OPERATING",
        "OPERATING",
        "OPERATING",
        "OPERATING",
        "OPERATING",
        "OPERATING",
        "OPERATING",
        "OPERATING",
        "OPERATING",
        "OPERATING",
        "OPERATING",
        "OPERATING",
        "OPERATING",
        "OPERATING",
        "OPERATING"
      ],
      "access_modes": [
        "STANDBY",
        "STANDBY",
        "STANDBY",
        "STANDBY",
        "STANDBY",
        "STANDBY",
        "STANDBY",
        "STANDBY",
        "STANDBY",
        "STANDBY",
        "STANDBY",
        "STANDBY",
        "STANDBY",
        "STANDBY",
        "STANDBY",
        "STANDBY",
        "STANDBY",
        "STANDBY",
        "STANDBY",
        "STANDBY",
        "STANDBY",
        "STANDBY",
        "STANDBY",
        "STANDBY",
        "STANDBY",
        "STANDBY",
        "STANDBY",
        "STANDBY",
        "STANDBY",
        "STANDBY"
      ]
    },
    "a-ak-13811": {
      "name_en": "Discovery Island Trails",
      "name_ja": "Discovery Island Trails",
      "waits": [
        null,
        null,
        null,
        null,
        null,
        null,
        null,
        null,
        null,
        null,
        null,
        null,
        null,
        null,
        null,
        null,
        null,
        null,
        null,
        null,
        null,
        null,
        null,
        null,
        null,
        null,
        null,
        null,
        null,
        null
      ],
      "opens": [
        true,
        true,
        true,
        true,
        true,
        true,
        true,
        true,
        true,
        true,
        true,
        true,
        true,
        true,
        true,
        true,
        true,
        false,
        false,
        false,
        false,
        false,
        false,
        false,
        false,
        false,
        false,
        false,
        false,
        false
      ],
      "statuses": [
        "OPERATING",
        "OPERATING",
        "OPERATING",
        "OPERATING",
        "OPERATING",
        "OPERATING",
        "OPERATING",
        "OPERATING",
        "OPERATING",
        "OPERATING",
        "OPERATING",
        "OPERATING",
        "OPERATING",
        "OPERATING",
        "OPERATING",
        "OPERATING",
        "OPERATING",
        "DOWN",
        "DOWN",
        "DOWN",
        "DOWN",
        "DOWN",
        "DOWN",
        "DOWN",
        "DOWN",
        "DOWN",
        "DOWN",
        "DOWN",
        "DOWN",
        "DOWN"
      ],
      "access_modes": [
        "STANDBY",
        "STANDBY",
        "STANDBY",
        "STANDBY",
        "STANDBY",
        "STANDBY",
        "STANDBY",
        "STANDBY",
        "STANDBY",
        "STANDBY",
        "STANDBY",
        "STANDBY",
        "STANDBY",
        "STANDBY",
        "STANDBY",
        "STANDBY",
        "STANDBY",
        "STANDBY",
        "STANDBY",
        "STANDBY",
        "STANDBY",
        "STANDBY",
        "STANDBY",
        "STANDBY",
        "STANDBY",
        "STANDBY",
        "STANDBY",
        "STANDBY",
        "STANDBY",
        "STANDBY"
      ]
    },
    "a-ak-116": {
      "name_en": "Meet Favorite Disney Pals at Adventurers Outpost",
      "name_ja": "Meet Favorite Disney Pals at Adventurers Outpost",
      "waits": [
        null,
        null,
        null,
        null,
        null,
        null,
        null,
        null,
        null,
        null,
        null,
        null,
        null,
        null,
        null,
        null,
        null,
        null,
        null,
        null,
        null,
        null,
        null,
        null,
        null,
        null,
        null,
        null,
        null,
        null
      ],
      "opens": [
        false,
        false,
        false,
        false,
        false,
        false,
        false,
        false,
        false,
        false,
        false,
        false,
        false,
        false,
        false,
        false,
        false,
        false,
        false,
        false,
        false,
        false,
        false,
        false,
        false,
        false,
        false,
        false,
        false,
        false
      ],
      "statuses": [
        "NO_INFO",
        "NO_INFO",
        "NO_INFO",
        "NO_INFO",
        "NO_INFO",
        "NO_INFO",
        "NO_INFO",
        "NO_INFO",
        "NO_INFO",
        "NO_INFO",
        "NO_INFO",
        "NO_INFO",
        "NO_INFO",
        "NO_INFO",
        "NO_INFO",
        "NO_INFO",
        "NO_INFO",
        "NO_INFO",
        "NO_INFO",
        "NO_INFO",
        "NO_INFO",
        "NO_INFO",
        "NO_INFO",
        "NO_INFO",
        "NO_INFO",
        "NO_INFO",
        "NO_INFO",
        "NO_INFO",
        "NO_INFO",
        "NO_INFO"
      ],
      "access_modes": [
        "STANDBY",
        "STANDBY",
        "STANDBY",
        "STANDBY",
        "STANDBY",
        "STANDBY",
        "STANDBY",
        "STANDBY",
        "STANDBY",
        "STANDBY",
        "STANDBY",
        "STANDBY",
        "STANDBY",
        "STANDBY",
        "STANDBY",
        "STANDBY",
        "STANDBY",
        "STANDBY",
        "STANDBY",
        "STANDBY",
        "STANDBY",
        "STANDBY",
        "STANDBY",
        "STANDBY",
        "STANDBY",
        "STANDBY",
        "STANDBY",
        "STANDBY",
        "STANDBY",
        "STANDBY"
      ]
    },
    "a-ak-12451": {
      "name_en": "Meet Moana at Character Landing",
      "name_ja": "Meet Moana at Character Landing",
      "waits": [
        null,
        null,
        null,
        null,
        null,
        null,
        null,
        null,
        null,
        null,
        null,
        null,
        null,
        null,
        null,
        null,
        null,
        null,
        null,
        null,
        null,
        null,
        null,
        null,
        null,
        null,
        null,
        null,
        null,
        null
      ],
      "opens": [
        false,
        true,
        true,
        true,
        true,
        true,
        true,
        true,
        true,
        true,
        true,
        true,
        true,
        true,
        true,
        true,
        true,
        false,
        false,
        false,
        false,
        false,
        false,
        false,
        false,
        false,
        false,
        false,
        false,
        false
      ],
      "statuses": [
        "NO_INFO",
        "OPERATING",
        "OPERATING",
        "OPERATING",
        "OPERATING",
        "OPERATING",
        "OPERATING",
        "OPERATING",
        "OPERATING",
        "OPERATING",
        "OPERATING",
        "OPERATING",
        "OPERATING",
        "OPERATING",
        "OPERATING",
        "OPERATING",
        "OPERATING",
        "DOWN",
        "DOWN",
        "DOWN",
        "DOWN",
        "DOWN",
        "DOWN",
        "DOWN",
        "DOWN",
        "DOWN",
        "DOWN",
        "DOWN",
        "DOWN",
        "DOWN"
      ],
      "access_modes": [
        "STANDBY",
        "STANDBY",
        "STANDBY",
        "STANDBY",
        "STANDBY",
        "STANDBY",
        "STANDBY",
        "STANDBY",
        "STANDBY",
        "STANDBY",
        "STANDBY",
        "STANDBY",
        "STANDBY",
        "STANDBY",
        "STANDBY",
        "STANDBY",
        "STANDBY",
        "STANDBY",
        "STANDBY",
        "STANDBY",
        "STANDBY",
        "STANDBY",
        "STANDBY",
        "STANDBY",
        "STANDBY",
        "STANDBY",
        "STANDBY",
        "STANDBY",
        "STANDBY",
        "STANDBY"
      ]
    },
    "a-ak-13751": {
      "name_en": "Tree of Life",
      "name_ja": "Tree of Life",
      "waits": [
        null,
        null,
        null,
        null,
        null,
        null,
        null,
        null,
        null,
        null,
        null,
        null,
        null,
        null,
        null,
        null,
        null,
        null,
        null,
        null,
        null,
        null,
        null,
        null,
        null,
        null,
        null,
        null,
        null,
        null
      ],
      "opens": [
        true,
        true,
        true,
        true,
        true,
        true,
        true,
        true,
        true,
        true,
        true,
        true,
        true,
        true,
        true,
        true,
        true,
        true,
        true,
        true,
        true,
        true,
        true,
        true,
        true,
        true,
        true,
        true,
        true,
        true
      ],
      "statuses": [
        "OPERATING",
        "OPERATING",
        "OPERATING",
        "OPERATING",
        "OPERATING",
        "OPERATING",
        "OPERATING",
        "OPERATING",
        "OPERATING",
        "OPERATING",
        "OPERATING",
        "OPERATING",
        "OPERATING",
        "OPERATING",
        "OPERATING",
        "OPERATING",
        "OPERATING",
        "OPERATING",
        "OPERATING",
        "OPERATING",
        "OPERATING",
        "OPERATING",
        "OPERATING",
        "OPERATING",
        "OPERATING",
        "OPERATING",
        "OPERATING",
        "OPERATING",
        "OPERATING",
        "OPERATING"
      ],
      "access_modes": [
        "STANDBY",
        "STANDBY",
        "STANDBY",
        "STANDBY",
        "STANDBY",
        "STANDBY",
        "STANDBY",
        "STANDBY",
        "STANDBY",
        "STANDBY",
        "STANDBY",
        "STANDBY",
        "STANDBY",
        "STANDBY",
        "STANDBY",
        "STANDBY",
        "STANDBY",
        "STANDBY",
        "STANDBY",
        "STANDBY",
        "STANDBY",
        "STANDBY",
        "STANDBY",
        "STANDBY",
        "STANDBY",
        "STANDBY",
        "STANDBY",
        "STANDBY",
        "STANDBY",
        "STANDBY"
      ]
    },
    "a-ak-14943": {
      "name_en": "Zootopia: Better Zoogether!",
      "name_ja": "Zootopia: Better Zoogether!",
      "waits": [
        null,
        null,
        null,
        null,
        null,
        null,
        null,
        null,
        null,
        null,
        null,
        null,
        null,
        null,
        null,
        null,
        null,
        null,
        null,
        null,
        null,
        null,
        null,
        null,
        null,
        null,
        null,
        null,
        null,
        null
      ],
      "opens": [
        false,
        false,
        false,
        false,
        false,
        false,
        false,
        false,
        false,
        false,
        false,
        false,
        false,
        false,
        false,
        false,
        false,
        false,
        false,
        false,
        false,
        false,
        false,
        false,
        false,
        false,
        false,
        false,
        false,
        false
      ],
      "statuses": [
        "NO_INFO",
        "NO_INFO",
        "NO_INFO",
        "NO_INFO",
        "NO_INFO",
        "NO_INFO",
        "NO_INFO",
        "NO_INFO",
        "NO_INFO",
        "NO_INFO",
        "NO_INFO",
        "NO_INFO",
        "NO_INFO",
        "NO_INFO",
        "NO_INFO",
        "NO_INFO",
        "NO_INFO",
        "NO_INFO",
        "NO_INFO",
        "NO_INFO",
        "NO_INFO",
        "NO_INFO",
        "NO_INFO",
        "NO_INFO",
        "NO_INFO",
        "NO_INFO",
        "NO_INFO",
        "NO_INFO",
        "NO_INFO",
        "NO_INFO"
      ],
      "access_modes": [
        "STANDBY",
        "STANDBY",
        "STANDBY",
        "STANDBY",
        "STANDBY",
        "STANDBY",
        "STANDBY",
        "STANDBY",
        "STANDBY",
        "STANDBY",
        "STANDBY",
        "STANDBY",
        "STANDBY",
        "STANDBY",
        "STANDBY",
        "STANDBY",
        "STANDBY",
        "STANDBY",
        "STANDBY",
        "STANDBY",
        "STANDBY",
        "STANDBY",
        "STANDBY",
        "STANDBY",
        "STANDBY",
        "STANDBY",
        "STANDBY",
        "STANDBY",
        "STANDBY",
        "STANDBY"
      ]
    },
    "a-ak-4439": {
      "name_en": "Avatar Flight of Passage",
      "name_ja": "アバター：フライト・オブ・パッセージ",
      "waits": [
        null,
        null,
        null,
        null,
        null,
        null,
        null,
        null,
        null,
        null,
        null,
        null,
        null,
        null,
        null,
        null,
        null,
        null,
        null,
        null,
        null,
        null,
        null,
        null,
        null,
        null,
        null,
        null,
        null,
        null
      ],
      "opens": [
        false,
        false,
        false,
        false,
        false,
        false,
        false,
        false,
        false,
        false,
        false,
        false,
        false,
        false,
        false,
        false,
        false,
        false,
        false,
        false,
        false,
        false,
        false,
        false,
        false,
        false,
        false,
        false,
        false,
        false
      ],
      "statuses": [
        "NO_INFO",
        "NO_INFO",
        "NO_INFO",
        "NO_INFO",
        "NO_INFO",
        "NO_INFO",
        "NO_INFO",
        "NO_INFO",
        "NO_INFO",
        "NO_INFO",
        "NO_INFO",
        "NO_INFO",
        "NO_INFO",
        "NO_INFO",
        "NO_INFO",
        "NO_INFO",
        "NO_INFO",
        "NO_INFO",
        "NO_INFO",
        "NO_INFO",
        "NO_INFO",
        "NO_INFO",
        "NO_INFO",
        "NO_INFO",
        "NO_INFO",
        "NO_INFO",
        "NO_INFO",
        "NO_INFO",
        "NO_INFO",
        "NO_INFO"
      ],
      "access_modes": [
        "STANDBY",
        "STANDBY",
        "STANDBY",
        "STANDBY",
        "STANDBY",
        "STANDBY",
        "STANDBY",
        "STANDBY",
        "STANDBY",
        "STANDBY",
        "STANDBY",
        "STANDBY",
        "STANDBY",
        "STANDBY",
        "STANDBY",
        "STANDBY",
        "STANDBY",
        "STANDBY",
        "STANDBY",
        "STANDBY",
        "STANDBY",
        "STANDBY",
        "STANDBY",
        "STANDBY",
        "STANDBY",
        "STANDBY",
        "STANDBY",
        "STANDBY",
        "STANDBY",
        "STANDBY"
      ]
    },
    "a-ak-4438": {
      "name_en": "Na'vi River Journey",
      "name_ja": "Na'vi River Journey",
      "waits": [
        null,
        null,
        null,
        null,
        null,
        null,
        null,
        null,
        null,
        null,
        null,
        null,
        null,
        null,
        null,
        null,
        null,
        null,
        null,
        null,
        null,
        null,
        null,
        null,
        null,
        null,
        null,
        null,
        null,
        null
      ],
      "opens": [
        false,
        false,
        false,
        false,
        false,
        false,
        false,
        false,
        false,
        false,
        false,
        false,
        false,
        false,
        false,
        false,
        false,
        false,
        false,
        false,
        false,
        false,
        false,
        false,
        false,
        false,
        false,
        false,
        false,
        false
      ],
      "statuses": [
        "NO_INFO",
        "NO_INFO",
        "NO_INFO",
        "NO_INFO",
        "NO_INFO",
        "NO_INFO",
        "NO_INFO",
        "NO_INFO",
        "NO_INFO",
        "NO_INFO",
        "NO_INFO",
        "NO_INFO",
        "NO_INFO",
        "NO_INFO",
        "NO_INFO",
        "NO_INFO",
        "NO_INFO",
        "NO_INFO",
        "NO_INFO",
        "NO_INFO",
        "NO_INFO",
        "NO_INFO",
        "NO_INFO",
        "NO_INFO",
        "NO_INFO",
        "NO_INFO",
        "NO_INFO",
        "NO_INFO",
        "NO_INFO",
        "NO_INFO"
      ],
      "access_modes": [
        "STANDBY",
        "STANDBY",
        "STANDBY",
        "STANDBY",
        "STANDBY",
        "STANDBY",
        "STANDBY",
        "STANDBY",
        "STANDBY",
        "STANDBY",
        "STANDBY",
        "STANDBY",
        "STANDBY",
        "STANDBY",
        "STANDBY",
        "STANDBY",
        "STANDBY",
        "STANDBY",
        "STANDBY",
        "STANDBY",
        "STANDBY",
        "STANDBY",
        "STANDBY",
        "STANDBY",
        "STANDBY",
        "STANDBY",
        "STANDBY",
        "STANDBY",
        "STANDBY",
        "STANDBY"
      ]
    },
    "a-ak-13812": {
      "name_en": "The Oasis Exhibits",
      "name_ja": "The Oasis Exhibits",
      "waits": [
        null,
        null,
        null,
        null,
        null,
        null,
        null,
        null,
        null,
        null,
        null,
        null,
        null,
        null,
        null,
        null,
        null,
        null,
        null,
        null,
        null,
        null,
        null,
        null,
        null,
        null,
        null,
        null,
        null,
        null
      ],
      "opens": [
        true,
        true,
        true,
        true,
        true,
        true,
        true,
        true,
        true,
        true,
        true,
        true,
        true,
        true,
        true,
        true,
        true,
        false,
        false,
        false,
        false,
        false,
        false,
        false,
        false,
        false,
        false,
        false,
        false,
        false
      ],
      "statuses": [
        "OPERATING",
        "OPERATING",
        "OPERATING",
        "OPERATING",
        "OPERATING",
        "OPERATING",
        "OPERATING",
        "OPERATING",
        "OPERATING",
        "OPERATING",
        "OPERATING",
        "OPERATING",
        "OPERATING",
        "OPERATING",
        "OPERATING",
        "OPERATING",
        "OPERATING",
        "DOWN",
        "DOWN",
        "DOWN",
        "DOWN",
        "DOWN",
        "DOWN",
        "DOWN",
        "DOWN",
        "DOWN",
        "DOWN",
        "DOWN",
        "DOWN",
        "DOWN"
      ],
      "access_modes": [
        "STANDBY",
        "STANDBY",
        "STANDBY",
        "STANDBY",
        "STANDBY",
        "STANDBY",
        "STANDBY",
        "STANDBY",
        "STANDBY",
        "STANDBY",
        "STANDBY",
        "STANDBY",
        "STANDBY",
        "STANDBY",
        "STANDBY",
        "STANDBY",
        "STANDBY",
        "STANDBY",
        "STANDBY",
        "STANDBY",
        "STANDBY",
        "STANDBY",
        "STANDBY",
        "STANDBY",
        "STANDBY",
        "STANDBY",
        "STANDBY",
        "STANDBY",
        "STANDBY",
        "STANDBY"
      ]
    },
    "a-ak-13808": {
      "name_en": "Wilderness Explorers",
      "name_ja": "Wilderness Explorers",
      "waits": [
        null,
        null,
        null,
        null,
        null,
        null,
        null,
        null,
        null,
        null,
        null,
        null,
        null,
        null,
        null,
        null,
        null,
        null,
        null,
        null,
        null,
        null,
        null,
        null,
        null,
        null,
        null,
        null,
        null,
        null
      ],
      "opens": [
        true,
        true,
        true,
        true,
        true,
        true,
        true,
        true,
        true,
        true,
        true,
        true,
        true,
        true,
        true,
        true,
        true,
        false,
        false,
        false,
        false,
        false,
        false,
        false,
        false,
        false,
        false,
        false,
        false,
        false
      ],
      "statuses": [
        "OPERATING",
        "OPERATING",
        "OPERATING",
        "OPERATING",
        "OPERATING",
        "OPERATING",
        "OPERATING",
        "OPERATING",
        "OPERATING",
        "OPERATING",
        "OPERATING",
        "OPERATING",
        "OPERATING",
        "OPERATING",
        "OPERATING",
        "OPERATING",
        "OPERATING",
        "DOWN",
        "DOWN",
        "DOWN",
        "DOWN",
        "DOWN",
        "DOWN",
        "DOWN",
        "DOWN",
        "DOWN",
        "DOWN",
        "DOWN",
        "DOWN",
        "DOWN"
      ],
      "access_modes": [
        "STANDBY",
        "STANDBY",
        "STANDBY",
        "STANDBY",
        "STANDBY",
        "STANDBY",
        "STANDBY",
        "STANDBY",
        "STANDBY",
        "STANDBY",
        "STANDBY",
        "STANDBY",
        "STANDBY",
        "STANDBY",
        "STANDBY",
        "STANDBY",
        "STANDBY",
        "STANDBY",
        "STANDBY",
        "STANDBY",
        "STANDBY",
        "STANDBY",
        "STANDBY",
        "STANDBY",
        "STANDBY",
        "STANDBY",
        "STANDBY",
        "STANDBY",
        "STANDBY",
        "STANDBY"
      ]
    }
  },
  "shows": []
}
